README.md
setup.py
neuroCombat/__init__.py
neuroCombat/neuroCombat.py
neuroCombat.egg-info/PKG-INFO
neuroCombat.egg-info/SOURCES.txt
neuroCombat.egg-info/dependency_links.txt
neuroCombat.egg-info/not-zip-safe
neuroCombat.egg-info/top_level.txt