Metadata-Version: 1.1
Name: neuroCombat
Version: 0.2.2
Summary: ComBat algorithm for harmonizing multi-site imaging data
Home-page: https://github.com/fortinj2/neuroCombat
Author: Jean-Philippe Fortin, Nick Cullen
Author-email: fortin946@gmail.com,
License: MIT license
Project-URL: Source Code, https://github.com/fortinj2/neuroCombat
Platform: UNKNOWN
Classifier: License :: OSI Approved :: MIT License
Classifier: Programming Language :: Python :: 3.7
